xml_sitemap_writer.py
xml_sitemap_writer-0.7.0.dist-info/licenses/LICENSE
xml_sitemap_writer-0.7.0.dist-info/METADATA
xml_sitemap_writer-0.7.0.dist-info/WHEEL
xml_sitemap_writer-0.7.0.dist-info/top_level.txt
xml_sitemap_writer-0.7.0.dist-info/RECORD
