Metadata-Version: 2.4
Name: xml_sitemap_writer
Version: 0.7.0
Summary: Python3 package for writing large XML sitemaps with no external dependencies
Home-page: https://github.com/pigs-will-fly/py-xml-sitemap-writer
Author: Maciej Brencz
Author-email: maciej.brencz@gmail.com
License: MIT
Classifier: Development Status :: 5 - Production/Stable
Classifier: License :: OSI Approved :: MIT License
Classifier: Programming Language :: Python :: 3
Requires-Python: >=3.9
License-File: LICENSE
Provides-Extra: dev
Requires-Dist: black==25.9.0; extra == "dev"
Requires-Dist: pylint==3.3.9; extra == "dev"
Requires-Dist: pytest==8.4.2; extra == "dev"
Requires-Dist: pytest-cov==7.0.0; extra == "dev"
Dynamic: author
Dynamic: author-email
Dynamic: classifier
Dynamic: description
Dynamic: description-content-type
Dynamic: home-page
Dynamic: license
Dynamic: license-file
Dynamic: provides-extra
Dynamic: requires-python
Dynamic: summary
